Metadata-Version: 2.4
Name: smart-code-analyzer
Version: 0.5.0
Summary: Deep source code analysis and documentation tool
Home-page: https://github.com/thinmanj/code-analyzer
Author: Julio
Classifier: Development Status :: 3 - Alpha
Classifier: Intended Audience :: Developers
Classifier: Topic :: Software Development :: Quality Assurance
Classifier: License :: OSI Approved :: MIT License
Classifier: Programming Language :: Python :: 3
Classifier: Programming Language :: Python :: 3.8
Classifier: Programming Language :: Python :: 3.9
Classifier: Programming Language :: Python :: 3.10
Classifier: Programming Language :: Python :: 3.11
Requires-Python: >=3.8
License-File: LICENSE
Requires-Dist: click>=8.0.0
Requires-Dist: pyyaml>=6.0
Requires-Dist: radon>=6.0.0
Requires-Dist: rich>=13.0.0
Requires-Dist: tqdm>=4.65.0
Provides-Extra: full
Requires-Dist: bandit>=1.7.0; extra == "full"
Requires-Dist: pylint>=2.17.0; extra == "full"
Requires-Dist: jedi>=0.19.0; extra == "full"
Provides-Extra: dev
Requires-Dist: pytest>=7.0.0; extra == "dev"
Requires-Dist: pytest-cov>=4.0.0; extra == "dev"
Requires-Dist: black>=22.0.0; extra == "dev"
Requires-Dist: mypy>=1.0.0; extra == "dev"
Dynamic: author
Dynamic: classifier
Dynamic: description
Dynamic: description-content-type
Dynamic: home-page
Dynamic: license-file
Dynamic: provides-extra
Dynamic: requires-dist
Dynamic: requires-python
Dynamic: summary
